<?xml version="1.0" encoding="UTF-8"?>
<!-- LISTA DE PRECIOS -->
<ListaPrecios numero="3">
<Proveedor>
<Cuil>6233</Cuil>
<RazonSocial>DXTV SRL</RazonSocial>
</Proveedor>
<Vigencia>
<Fecha>01/06/2014</Fecha>
<Termino>60</Termino>
</Vigencia>
<CondicionesDeVenta>
<PagoContado>
<Descuento>23</Descuento>
</PagoContado>
<Financiacion>
<Dias>30</Dias>
<Recargo>14</Recargo>
</Financiacion>
<Financiacion>
<Dias>60</Dias>
<Recargo>22</Recargo>
</Financiacion>
<Financiacion>
<Dias>90</Dias>
<Recargo>33</Recargo>
</Financiacion>
</CondicionesDeVenta>
<Rodamientos>
<Item>
<Codigo>9</Codigo>
<Sufijo>MN</Sufijo>
<Marca>SFR</Marca>
<Origen>Argentina</Origen>
<Tipo>Tuerca</Tipo>
<Medida>0.6</Medida>
<Caracteristica>124</Caracteristica>
<Precio>55.00</Precio>
<Cantidad>104</Cantidad>
</Item>
<Item>
<Codigo>10</Codigo>
<Sufijo>MN</Sufijo>
<Marca>FDMX</Marca>
<Origen>Brasil</Origen>
<Tipo>Bolilla</Tipo>
<Medida>0.8</Medida>
<Caracteristica>437</Caracteristica>
<Precio>235.00</Precio>
<Cantidad>400</Cantidad>
</Item>
<Item>
<Codigo>11</Codigo>
<Sufijo>MN</Sufijo>
<Marca>GRTN</Marca>
<Origen>Marruecos</Origen>
<Tipo>Tornillo</Tipo>
<Medida>0.3</Medida>
<Caracteristica>514</Caracteristica>
<Precio>135.00</Precio>
<Cantidad>59</Cantidad>
</Item>
<Item>
<Codigo>12</Codigo>
<Sufijo>MN</Sufijo>
<Marca>MGK</Marca>
<Origen>Suecia</Origen>
<Tipo>Rizon</Tipo>
<Medida>0.6</Medida>
<Caracteristica>1239</Caracteristica>
<Precio>80.00</Precio>
<Cantidad>170</Cantidad>
</Item>
<Item>
<Codigo>5</Codigo>
<Sufijo>MN</Sufijo>
<Marca>FAG</Marca>
<Origen>Rumania</Origen>
<Tipo>Rueda</Tipo>
<Medida>2.7</Medida>
<Caracteristica>434</Caracteristica>
<Precio>60.00</Precio>
<Cantidad>46</Cantidad>
</Item>
</Rodamientos>
</ListaPrecios>